{
    "data": {
        "lend": {
            "loan": {
                "id": 1780314,
                "name": "Miguel Angel",
                "loanAmount": "1200.00",
                "paidAmount": "0.00",
                "status": "funded",
                "fundraisingDate": "2019-06-15T10:10:06Z",
                "disbursalDate": "2019-06-06T07:00:00Z",
                "plannedExpirationDate": "2019-07-19T16:01:34Z",
                "distributionModel": "fieldPartner",
                "use": "to buy more animals such as chickens, ducks and pigs, and food for them.",
                "description": "Miguel Angel is 41 years old. He is in a common-law marriage. He lives with his partner in the district of Cayaltí, Chiclayo province, department of Lambayeque, Peru. He has very good personal and work references from people in the neighbourhood. The residents here predominantly work in farming, commerce and ranching. <br /><br />He makes a living rearing and selling pigs, with more than 19 years experience in this field. He is requesting a loan to buy more animals such as chickens, ducks and pigs, and food for them. By doing so he can make a greater income for him and his family.<br /><br />Miguel Angel is a returning member of Edpyme Alternativa.",
                "tags": [
                    "user_favorite",
                    "#Sustainable Ag",
                    "#Animals",
                    "#Repeat Borrower"
                ],
                "matchRatio": null,
                "isMatchable": false,
                "borrowerCount": 1,
                "whySpecial": "It reaches the underserved.",
                "hasCurrencyExchangeLossLenders": false,
                "matchingText": "",
                "image": {
                    "url": "1360kivaImages/1780314.jpg"
                },
                "video": null,
                "geocode": {
                    "country": {
                        "isoCode": "PE",
                        "name": "Peru"
                    }
                },
                "lenders": {
                    "totalCount": 41,
                    "values": []
                },
                "activity": {
                    "name": "Pigs"
                },
                "sector": {
                    "name": "Agriculture"
                },
                "partnerName": "Edpyme Alternativa"
            }
        }
    }
}